configstore/__init__.py
configstore/util.py
example/__init__.py
example/config_manager.py
config_store-0.0.4.dist-info/LICENSE
config_store-0.0.4.dist-info/METADATA
config_store-0.0.4.dist-info/WHEEL
config_store-0.0.4.dist-info/top_level.txt
config_store-0.0.4.dist-info/RECORD
