Metadata-Version: 2.1
Name: config-store
Version: 0.0.4
Summary: A python module for env variable and config file management.
Home-page: https://github.com/ZhongTing/config-store
Author: Felix ZongTing
Author-email: gary62107@gmail.com
License: UNKNOWN
Platform: UNKNOWN
Classifier: Programming Language :: Python :: 3
Classifier: License :: OSI Approved :: MIT License
Classifier: Operating System :: OS Independent
